methodtools.py
methodtools-0.1.0.dist-info/LICENSE
methodtools-0.1.0.dist-info/METADATA
methodtools-0.1.0.dist-info/WHEEL
methodtools-0.1.0.dist-info/top_level.txt
methodtools-0.1.0.dist-info/RECORD
