Metadata-Version: 2.1
Name: methodtools
Version: 0.1.0
Summary: Expand standard functools to methods
Home-page: https://github.com/youknowone/methodtools
Author: Jeong YunWon
Author-email: methodtools@youknowone.org
License: UNKNOWN
Platform: UNKNOWN
Classifier: Intended Audience :: Developers
Classifier: Operating System :: OS Independent
Classifier: License :: OSI Approved :: BSD License
Classifier: Programming Language :: Python
Classifier: Programming Language :: Python :: 2
Classifier: Programming Language :: Python :: 2.7
Classifier: Programming Language :: Python :: 3
Classifier: Programming Language :: Python :: 3.4
Classifier: Programming Language :: Python :: 3.5
Classifier: Programming Language :: Python :: 3.6
Classifier: Programming Language :: Python :: 3.7
Requires-Dist: wirerope (>=0.2.1)
Provides-Extra: dev
Requires-Dist: pytest (>=3.0.2) ; extra == 'dev'
Requires-Dist: pytest-cov ; extra == 'dev'
Requires-Dist: functools32 (>=3.2.3-2) ; extra == 'dev'
Requires-Dist: sphinx ; extra == 'dev'
Provides-Extra: docs
Requires-Dist: sphinx ; extra == 'docs'
Provides-Extra: tests
Requires-Dist: pytest (>=3.0.2) ; extra == 'tests'
Requires-Dist: pytest-cov ; extra == 'tests'
Requires-Dist: functools32 (>=3.2.3-2) ; extra == 'tests'
